README.md
setup.py
superorm/__init__.py
superorm/dao.py
superorm/engine.py
superorm/factory.py
superorm/handler.py
superorm/logger.py
superorm/manager.py
superorm/mapper.py
superorm/orm.py
superorm/pool.py
superorm/session.py
superorm/wraps.py
superorm.egg-info/PKG-INFO
superorm.egg-info/SOURCES.txt
superorm.egg-info/dependency_links.txt
superorm.egg-info/not-zip-safe
superorm.egg-info/requires.txt
superorm.egg-info/top_level.txt